{
  "intro": [
    {
      "id": 1,
      "text": "Bonjour mon ami, tu te demandes sûrement ce que tu fais là!",
      "audio": "dialog1.mp3"
    },
    {
      "id": 2,
      "text": "Bonjour mon ami, tu te demandes sûrement ce que tu fais là!",
      "audio": "dialog1.mp3"
    },
    {
      "id": 3,
      "text": "Bonjour mon ami, tu te demandes sûrement ce que tu fais là!",
      "audio": "dialog1.mp3"
    },
    {
      "id": 4,
      "text": "Bonjour mon ami, tu te demandes sûrement ce que tu fais là!",
      "audio": "dialog1.mp3",
      "choices": [
        {
          "proposition": "Je me demande surtout qui tu es ! ",
          "response": "Comment ça ? Qui je suis ? Je m’appelle Dr. Deck, mais on se fiche de savoir qui je suis! Ce qui est important c’est l’environnement dans lequel tu te trouves."
        },
        {
          "proposition": "Choix 2  ",
          "response": " Réponse 2 Comment ça ? Qui je suis ? Je m’appelle Dr. Deck, mais on se fiche de savoir qui je suis! Ce qui est important c’est l’environnement dans lequel tu te trouves."
        }
      ]
    },
    {
      "id": 5,
      "text": "Bonjour mon ami, tu te demandes sûrement ce que tu fais là!",
      "audio": "dialog1.mp3",
      "choices": [
        {
          "proposition": "Je me demande surtout qui tu es ! ",
          "response": "Comment ça ? Qui je suis ? Je m’appelle Dr. Deck, mais on se fiche de savoir qui je suis! Ce qui est important c’est l’environnement dans lequel tu te trouves.",
          "switchToGame": "colorPicker"
        }
      ]
    }
  ]
}
